django_simple_notes/__init__.py
django_simple_notes/admin.py
django_simple_notes/apps.py
django_simple_notes/cms_toolbars.py
django_simple_notes/models.py
django_simple_notes/conf/__init__.py
django_simple_notes/conf/settings.py
django_simple_notes/locale/fr/LC_MESSAGES/django.mo
django_simple_notes/locale/fr/LC_MESSAGES/django.po
django_simple_notes/migrations/0001_initial.py
django_simple_notes/migrations/0002_auto_20230615_1805.py
django_simple_notes/migrations/0003_auto_20230620_1207.py
django_simple_notes/migrations/0004_auto_20230620_1452.py
django_simple_notes/migrations/0005_auto_20231030_1751.py
django_simple_notes/migrations/0006_auto_20240417_1640.py
django_simple_notes/migrations/__init__.py
django_simple_notes/templatetags/__init__.py
django_simple_notes/templatetags/django_simple_notes.py
django_simple_notes-1.0.5.dist-info/LICENSE
django_simple_notes-1.0.5.dist-info/METADATA
django_simple_notes-1.0.5.dist-info/WHEEL
django_simple_notes-1.0.5.dist-info/top_level.txt
django_simple_notes-1.0.5.dist-info/RECORD
