Metadata-Version: 2.1
Name: django-simple-notes
Version: 1.0.5
Summary: Store simple notes linked to Django(-cms) pages. Supports apphooks (but not custom apps)!
Home-page: https://gitlab.com/kapt/open-source/django-simple-notes
Author: Dev Kapt
Author-email: dev@kapt.mobi
Project-URL: Documentation, https://gitlab.com/kapt/open-source/django-simple-notes/-/blob/main/README.md
Project-URL: Release notes, https://gitlab.com/kapt/open-source/django-simple-notes/-/blob/main/CHANGELOG.rst
Project-URL: Tracker, https://gitlab.com/kapt/open-source/django-simple-notes/-/issues
Keywords: django,django-cms
Classifier: Environment :: Web Environment
Classifier: Framework :: Django
Classifier: Framework :: Django :: 2.2
Classifier: Framework :: Django :: 3.1
Classifier: Intended Audience :: Developers
Classifier: License :: OSI Approved :: GNU General Public License v3 (GPLv3)
Classifier: Programming Language :: Python
Classifier: Programming Language :: Python :: 3
Classifier: Topic :: Internet :: WWW/HTTP
Classifier: Topic :: Internet :: WWW/HTTP :: Dynamic Content
Requires-Python: >=3
License-File: LICENSE
Requires-Dist: django-cms
Requires-Dist: django-filer
Requires-Dist: django-ckeditor
Requires-Dist: django-ckeditor-filebrowser-filer
